tests/__init__.py
tests/test_cli.py
xerus/__init__.py
xerus/agent.py
xerus/cli.py
xerus/config.py
xerus/error_handler.py
xerus/errors.py
xerus/model.py
xerus/sessions.py
xerus/utils.py
xerus/commands/__init__.py
xerus/commands/chat.py
xerus/commands/init.py
xerus/commands/run.py
xerus/commands/sessions.py
xerus/tools/__init__.py
xerus/tools/builtin_manager.py
xerus/tools/factory.py
xerus/tools/importer.py
xerus/tools/manager_factory.py
xerus/tools/mcp_manager.py
xerus/ui/__init__.py
xerus/ui/display.py
xerus/ui/progress.py
xerus_ai-0.0.7.dist-info/licenses/LICENSE
xerus_ai-0.0.7.dist-info/METADATA
xerus_ai-0.0.7.dist-info/WHEEL
xerus_ai-0.0.7.dist-info/entry_points.txt
xerus_ai-0.0.7.dist-info/top_level.txt
xerus_ai-0.0.7.dist-info/RECORD
