Metadata-Version: 2.4
Name: xerus-ai
Version: 0.0.7
Summary: CLI agent for for running CodeAct agents, built with Huggingface Smolagents
Author-email: Ulan Abdurazakov <ylankgz@gmail.com>
License: MIT
Project-URL: Homepage, https://github.com/ylankgz/xerus
Project-URL: Repository, https://github.com/ylankgz/xerus
Classifier: Programming Language :: Python :: 3
Classifier: License :: OSI Approved :: MIT License
Classifier: Operating System :: OS Independent
Requires-Python: >=3.10
License-File: LICENSE
Requires-Dist: smolagents[litellm,toolkit]>=1.15.0
Requires-Dist: rich-click>=1.8.8
Requires-Dist: python-dotenv>=1.1.0
Requires-Dist: mcp>=1.9.2
Dynamic: license-file
